rag_blueprint/__init__.py
rag_blueprint/cli.py
rag_blueprint/generator.py
rag_blueprint/py.typed
rag_blueprint/templates/advanced/.env.example
rag_blueprint/templates/advanced/README.md.j2
rag_blueprint/templates/advanced/data/.keep
rag_blueprint/templates/advanced/main.py.j2
rag_blueprint/templates/advanced/requirements.txt.j2
rag_blueprint/templates/agentic/.env.example
rag_blueprint/templates/agentic/README.md.j2
rag_blueprint/templates/agentic/agent.py.j2
rag_blueprint/templates/agentic/data/.keep
rag_blueprint/templates/agentic/main.py.j2
rag_blueprint/templates/agentic/requirements.txt.j2
rag_blueprint/templates/agentic/tools.py.j2
rag_blueprint/templates/simple/.env.example
rag_blueprint/templates/simple/.keep
rag_blueprint/templates/simple/README.md.j2
rag_blueprint/templates/simple/data/.keep
rag_blueprint/templates/simple/main.py.j2
rag_blueprint/templates/simple/requirements.txt.j2
rag_blueprint-0.1.0.dist-info/WHEEL
rag_blueprint-0.1.0.dist-info/entry_points.txt
rag_blueprint-0.1.0.dist-info/METADATA
rag_blueprint-0.1.0.dist-info/RECORD
