Metadata-Version: 2.3
Name: rag-blueprint
Version: 0.1.0
Summary: Add your description here
Author: mdnu838
Author-email: mdnu838 <mdnu838@gmail.com>
Requires-Dist: jinja2>=3.1.6
Requires-Dist: rich>=14.2.0
Requires-Dist: typer>=0.21.1
Requires-Python: >=3.13
